woodw_toolkit/__init__.py
woodw_toolkit/common/__init__.py
woodw_toolkit/common/dt.py
woodw_toolkit/common/func.py
woodw_toolkit/common/io_util.py
woodw_toolkit/conf/__init__.py
woodw_toolkit/main/__init__.py
woodw_toolkit/main/llm_service_test.py
woodw_toolkit/main/main.py
woodw_toolkit/services/__init__.py
woodw_toolkit/services/llm_service.py
woodw_toolkit/tests/__init__.py
woodw_toolkit-0.1.2.dist-info/LICENSE
woodw_toolkit-0.1.2.dist-info/METADATA
woodw_toolkit-0.1.2.dist-info/WHEEL
woodw_toolkit-0.1.2.dist-info/top_level.txt
woodw_toolkit-0.1.2.dist-info/RECORD
