Metadata-Version: 2.2
Name: woodw-toolkit
Version: 0.1.2
Summary: It is a toolkit that includes various common operations and will continue to be improved in the future.
Home-page: https://gitee.com/jinghewang/python-woodw-toolkit.git
Author: jinghewang
Author-email: jinghewang@163.com
License: MIT License
Classifier: Programming Language :: Python :: 3
Classifier: License :: OSI Approved :: MIT License
Classifier: Operating System :: OS Independent
Requires-Python: >=3.9
License-File: LICENSE
Dynamic: author
Dynamic: author-email
Dynamic: classifier
Dynamic: description
Dynamic: description-content-type
Dynamic: home-page
Dynamic: license
Dynamic: requires-python
Dynamic: summary
